[

      {
        "rank": 50,
        "displayName": "Mauricio",
        "message": "Seek truth",
        "image": "mauricio.png",
        "links": {
          "twitter": "PetoVeritas",
          "nostr": "npub10htqtrkhcztsel8e3zka259npr4s2gx8mfaj676hvmu9vt0c7hyqu0smgf"
        },
        "blockHeight": 917054
      },
      {
        "rank": 200,
        "displayName": "TimSmig",        
        "image": "timsmig.png",
        "links": {
          "twitter": "timsmig"
        },
        "blockHeight": 920121
      },
      {
        "rank": 25,
        "displayName": "Secure Sovereign",        
        "image": "secsov.png",
        "links": {
          "twitter": "secsovereign"
        },
        "blockHeight": 921687
      },
      {
        "rank": 20,
        "displayName": "TKay",        
        "image": "tkay.png",
        "message": "Stay Sovereign",
        "links": {
          "nostr": "npub1nje4ghpkjsxe5thcd4gdt3agl2usxyxv3xxyx39ul3xgytl5009q87l02j"
        },
        "blockHeight": 928907
      }

]

